setup.cfg
setup.py
table_string_sqlite_cell/__init__.py
table_string_sqlite_cell/__main__.py
table_string_sqlite_cell/main.py
table_string_sqlite_cell.egg-info/PKG-INFO
table_string_sqlite_cell.egg-info/SOURCES.txt
table_string_sqlite_cell.egg-info/dependency_links.txt
table_string_sqlite_cell.egg-info/entry_points.txt
table_string_sqlite_cell.egg-info/requires.txt
table_string_sqlite_cell.egg-info/top_level.txt