Metadata-Version: 1.1
Name: table-string-sqlite-cell
Version: 0.5
Summary: create a single cell table with a value
Home-page: https://github.com/NCI-GDC/table_string_sqlite_cell
Author: Jeremiah H. Savage
Author-email: jeremiahsavage@gmail.com
License: Apache 2.0
Platform: UNKNOWN
Classifier: Development Status :: 3 - Alpha
Classifier: Intended Audience :: Developers
Classifier: License :: OSI Approved :: Apache Software License
Classifier: Programming Language :: Python
Classifier: Programming Language :: Python :: 2
Classifier: Programming Language :: Python :: 3
